siokcp/__init__.py
siokcp/_kcp.c
siokcp/kcp.pxd
siokcp/_kcp.pyx
siokcp/_kcp.cpython-311-x86_64-linux-musl.so
siokcp/asyncio/__init__.py
siokcp/asyncio/protocol.py
siokcp/asyncio/server.py
siokcp/asyncio/client.py
siokcp/asyncio/transport.py
siokcp/asyncio/utils.py
siokcp-0.0.5.dist-info/WHEEL
siokcp-0.0.5.dist-info/top_level.txt
siokcp-0.0.5.dist-info/METADATA
siokcp-0.0.5.dist-info/RECORD
